CpythonGeiDaxueshengDeRumenjiaochengFix1/README.md
CpythonGeiDaxueshengDeRumenjiaochengFix1/__init__.py
CpythonGeiDaxueshengDeRumenjiaochengFix1/__main__.py
CpythonGeiDaxueshengDeRumenjiaochengFix1/file.epub
CpythonGeiDaxueshengDeRumenjiaochengFix1/index.html
CpythonGeiDaxueshengDeRumenjiaochengFix1/css/__init__.py
CpythonGeiDaxueshengDeRumenjiaochengFix1/css/annotations.css
CpythonGeiDaxueshengDeRumenjiaochengFix1/css/main.css
CpythonGeiDaxueshengDeRumenjiaochengFix1/css/normalize.css
CpythonGeiDaxueshengDeRumenjiaochengFix1/css/popup.css
CpythonGeiDaxueshengDeRumenjiaochengFix1/font/__init__.py
CpythonGeiDaxueshengDeRumenjiaochengFix1/font/fontello.eot
CpythonGeiDaxueshengDeRumenjiaochengFix1/font/fontello.svg
CpythonGeiDaxueshengDeRumenjiaochengFix1/font/fontello.ttf
CpythonGeiDaxueshengDeRumenjiaochengFix1/font/fontello.woff
CpythonGeiDaxueshengDeRumenjiaochengFix1/img/__init__.py
CpythonGeiDaxueshengDeRumenjiaochengFix1/img/annotator-glyph-sprite.png
CpythonGeiDaxueshengDeRumenjiaochengFix1/img/annotator-icon-sprite.png
CpythonGeiDaxueshengDeRumenjiaochengFix1/img/apple-touch-icon.png
CpythonGeiDaxueshengDeRumenjiaochengFix1/img/cancelfullscreen.png
CpythonGeiDaxueshengDeRumenjiaochengFix1/img/close.png
CpythonGeiDaxueshengDeRumenjiaochengFix1/img/fullscreen.png
CpythonGeiDaxueshengDeRumenjiaochengFix1/img/loader.gif
CpythonGeiDaxueshengDeRumenjiaochengFix1/img/menu-icon.png
CpythonGeiDaxueshengDeRumenjiaochengFix1/img/save.png
CpythonGeiDaxueshengDeRumenjiaochengFix1/img/saved.png
CpythonGeiDaxueshengDeRumenjiaochengFix1/img/settings-s.png
CpythonGeiDaxueshengDeRumenjiaochengFix1/img/settings.png
CpythonGeiDaxueshengDeRumenjiaochengFix1/img/star.png
CpythonGeiDaxueshengDeRumenjiaochengFix1/js/__init__.py
CpythonGeiDaxueshengDeRumenjiaochengFix1/js/epub.js
CpythonGeiDaxueshengDeRumenjiaochengFix1/js/epub.min.js
CpythonGeiDaxueshengDeRumenjiaochengFix1/js/epub.min.map
CpythonGeiDaxueshengDeRumenjiaochengFix1/js/hooks.min.js
cpython_gei_daxuesheng_de_rumenjiaocheng_fix1-2025.3.24.0.dist-info/METADATA
cpython_gei_daxuesheng_de_rumenjiaocheng_fix1-2025.3.24.0.dist-info/WHEEL
cpython_gei_daxuesheng_de_rumenjiaocheng_fix1-2025.3.24.0.dist-info/entry_points.txt
cpython_gei_daxuesheng_de_rumenjiaocheng_fix1-2025.3.24.0.dist-info/top_level.txt
cpython_gei_daxuesheng_de_rumenjiaocheng_fix1-2025.3.24.0.dist-info/RECORD
